spy/__init__.py
spy/__main__.py
spy/catcher.py
spy/cli.py
spy/core.py
spy/decorators.py
spy/fragments.py
spy/objects.py
spy/prelude.py
spy_cli-0.5.0.dist-info/LICENSE
spy_cli-0.5.0.dist-info/METADATA
spy_cli-0.5.0.dist-info/WHEEL
spy_cli-0.5.0.dist-info/entry_points.txt
spy_cli-0.5.0.dist-info/top_level.txt
spy_cli-0.5.0.dist-info/zip-safe
spy_cli-0.5.0.dist-info/RECORD
