Metadata-Version: 2.1
Name: spy-cli
Version: 0.5.0
Summary: stream processing Python CLI
Home-page: https://github.com/edk0/spy/
Author: Ed Kellett
Author-email: e@kellett.im
License: UNKNOWN
Project-URL: Documentation, https://spy.readthedocs.io/
Platform: UNKNOWN
Classifier: Development Status :: 3 - Alpha
Classifier: Environment :: Console
Classifier: Intended Audience :: Developers
Classifier: License :: Public Domain
Classifier: Operating System :: OS Independent
Classifier: Programming Language :: Python :: 3
Classifier: Programming Language :: Python :: 3.4
Classifier: Programming Language :: Python :: 3.5
Classifier: Programming Language :: Python :: 3.6
Classifier: Programming Language :: Python :: 3.7
Classifier: Programming Language :: Python :: 3.8
Classifier: Topic :: Utilities
Requires-Python: >=3.4
Requires-Dist: clize (>=3.0)
Provides-Extra: test
Requires-Dist: pytest (>=5.0) ; extra == 'test'
Requires-Dist: pytest-cov ; extra == 'test'
Requires-Dist: coverage ; extra == 'test'
Requires-Dist: lenses ; extra == 'test'
